quantnn/__init__.py
quantnn/a_priori.py
quantnn/common.py
quantnn/data.py
quantnn/density.py
quantnn/drnn.py
quantnn/metrics.py
quantnn/mrnn.py
quantnn/neural_network_model.py
quantnn/normalizer.py
quantnn/packed_tensor.py
quantnn/plotting.py
quantnn/qrnn.py
quantnn/quantiles.py
quantnn/transformations.py
quantnn/utils.py
quantnn/backends/__init__.py
quantnn/backends/pytorch.py
quantnn/backends/tensor.py
quantnn/data/matplotlib_style.rc
quantnn/examples/__init__.py
quantnn/examples/gprof_conv.py
quantnn/examples/gprof_simple.py
quantnn/examples/modis_ctp.py
quantnn/examples/simple.py
quantnn/files/__init__.py
quantnn/files/sftp.py
quantnn/generic/__init__.py
quantnn/logging/__init__.py
quantnn/logging/multiprocessing.py
quantnn/models/__init__.py
quantnn/models/keras/__init__.py
quantnn/models/keras/padding.py
quantnn/models/keras/unet.py
quantnn/models/keras/xception.py
quantnn/models/pytorch/__init__.py
quantnn/models/pytorch/aggregators.py
quantnn/models/pytorch/blocks.py
quantnn/models/pytorch/common.py
quantnn/models/pytorch/decoders.py
quantnn/models/pytorch/encoders.py
quantnn/models/pytorch/factories.py
quantnn/models/pytorch/fully_connected.py
quantnn/models/pytorch/generative.py
quantnn/models/pytorch/lightning.py
quantnn/models/pytorch/logging.py
quantnn/models/pytorch/resnet.py
quantnn/models/pytorch/stages.py
quantnn/models/pytorch/torchvision.py
quantnn/models/pytorch/unet.py
quantnn/models/pytorch/upsampling.py
quantnn/models/pytorch/xception.py
quantnn-0.0.5.dist-info/LICENSE
quantnn-0.0.5.dist-info/METADATA
quantnn-0.0.5.dist-info/WHEEL
quantnn-0.0.5.dist-info/top_level.txt
quantnn-0.0.5.dist-info/RECORD
