Metadata-Version: 2.1
Name: quantnn
Version: 0.0.5
Summary: Quantile regression neural networks.
Home-page: https://github.com/simonpf/quantnn
Author: Simon Pfreundschuh
License: UNKNOWN
Platform: UNKNOWN
Classifier: Programming Language :: Python :: 3
Classifier: Operating System :: OS Independent
Requires-Python: >=3.6
Requires-Dist: numpy
Requires-Dist: scipy
Requires-Dist: xarray
Requires-Dist: paramiko
Requires-Dist: einops
Requires-Dist: matplotlib
Requires-Dist: rich
